setup.py
odatoo/__init__.py
odatoo/document.py
odatoo/errors.py
odatoo/field.py
odatoo/record.py
odatoo.egg-info/PKG-INFO
odatoo.egg-info/SOURCES.txt
odatoo.egg-info/dependency_links.txt
odatoo.egg-info/top_level.txt
tests/__init__.py
tests/test_document.py
tests/test_field.py
tests/test_record.py