Metadata-Version: 1.1
Name: odatoo
Version: 0.3
Summary: Odoo XML data files library
Home-page: https://github.com/wearp/odatoo
Author: Will Earp
Author-email: will.earp@icloud.com
License: UNKNOWN
Download-URL: https://github.com/wearp/odatoo/tarball/0.3
Keywords: odoo,xml,data,files
Platform: UNKNOWN
